setup.cfg
setup.py
asamended/__init__.py
asamended/config.py
asamended/utils.py
asamended.egg-info/PKG-INFO
asamended.egg-info/SOURCES.txt
asamended.egg-info/dependency_links.txt
asamended.egg-info/requires.txt
asamended.egg-info/top_level.txt
asamended/uscode/__init__.py
asamended/uscode/client.py
asamended/uscode/ident.py
asamended/uscode/node.py
asamended/uscode/search.py
asamended/uscode/user.py