Metadata-Version: 1.0
Name: asamended
Version: 0.04
Summary: Client library for the asamended.com API.
Home-page: http://asamended.github.com/python-asamended/
Author: Thom Neale
Author-email: twneale@gmail.com
License: MIT
Platform: any
